easy_net/__init__.py
easy_net/errors.py
easy_net/models.py
easy_net/server.py
tests/__init__.py
tests/protocol_for_tests.py
tests/test_main.py
easy_net-1.2.4.dist-info/LICENSE
easy_net-1.2.4.dist-info/METADATA
easy_net-1.2.4.dist-info/WHEEL
easy_net-1.2.4.dist-info/top_level.txt
easy_net-1.2.4.dist-info/RECORD
